<?xml version="1.0" encoding="UTF-8"?>
<EnvelopePresetTable doc_version="0">
  <PresetVersion>3.15</PresetVersion>
  <Scheme/>
  <PointSequences/>
  <Frequency>00</Frequency>
  <FrequencyMode>00</FrequencyMode>
  <LoopMode>00</LoopMode>
  <NoteDrawType>1</NoteDrawType>
  <NoteScheme>0,-12,2222</NoteScheme>
  <NotePointSequences>0,4,8</NotePointSequences>
  <NoteSchemeSize>8</NoteSchemeSize>
  <NoteFrequency>1</NoteFrequency>
  <NoteFrequencyMode>1</NoteFrequencyMode>
  <NoteLoopMode>1</NoteLoopMode>
  <NoteLoopType>2</NoteLoopType>
  <NoteLoopStart>0</NoteLoopStart>
  <NoteLoopEnd>8</NoteLoopEnd>
  <NoteSustain>-1</NoteSustain>
  <NoteLFOApply>false</NoteLFOApply>
  <NoteLFO1>1</NoteLFO1>
  <NoteLFOPhase1>0</NoteLFOPhase1>
  <NoteLFOFrequency1>3</NoteLFOFrequency1>
  <NoteLFOAmount1>27</NoteLFOAmount1>
  <NoteLFO2>1</NoteLFO2>
  <NoteLFOPhase2>0</NoteLFOPhase2>
  <NoteLFOFrequency2>3</NoteLFOFrequency2>
  <NoteLFOAmount2>27</NoteLFOAmount2>
  <ToneFactor>3</ToneFactor>
  <Transpose>-12.24</Transpose>
  <TransposeLink>false</TransposeLink>
  <LoopAssistance>1</LoopAssistance>
  <VolumeScheme>100,50</VolumeScheme>
  <VolumePointSequences>0,1</VolumePointSequences>
  <VolumeSchemeSize>5</VolumeSchemeSize>
  <VolumeDrawType>1</VolumeDrawType>
  <VolumeFrequency>0</VolumeFrequency>
  <VolumeFrequencyMode>3</VolumeFrequencyMode>
  <VolumeApply>true</VolumeApply>
  <VolumeLoopMode>1</VolumeLoopMode>
  <VolumeLoopType>1</VolumeLoopType>
  <VolumeLoopStart>4</VolumeLoopStart>
  <VolumeLoopEnd>6</VolumeLoopEnd>
  <VolumeSustain>0</VolumeSustain>
  <VolumePulseMode>1</VolumePulseMode>
  <VolumeHighValue>100</VolumeHighValue>
  <VolumeLowValue>54</VolumeLowValue>
  <VolumeHighSize>0</VolumeHighSize>
  <VolumeRelease>321</VolumeRelease>
  <VolumeLFOApply>false</VolumeLFOApply>
  <VolumeLFO1>1</VolumeLFO1>
  <VolumeLFOPhase1>0</VolumeLFOPhase1>
  <VolumeLFOFrequency1>1</VolumeLFOFrequency1>
  <VolumeLFOAmount1>27</VolumeLFOAmount1>
  <VolumeLFO2>1</VolumeLFO2>
  <VolumeLFOPhase2>0</VolumeLFOPhase2>
  <VolumeLFOFrequency2>3</VolumeLFOFrequency2>
  <VolumeLFOAmount2>27</VolumeLFOAmount2>
  <PanningScheme/>
  <PanningPointSequences/>
  <PanningSchemeSize>49</PanningSchemeSize>
  <PanningDrawType>3</PanningDrawType>
  <PanningFrequency>0</PanningFrequency>
  <PanningFrequencyMode>3</PanningFrequencyMode>
  <PanningApply>false</PanningApply>
  <PanningLoopMode>1</PanningLoopMode>
  <PanningLoopType>2</PanningLoopType>
  <PanningLoopStart>1</PanningLoopStart>
  <PanningLoopEnd>49</PanningLoopEnd>
  <PanningSustain>-1</PanningSustain>
  <PanningPulseMode>1</PanningPulseMode>
  <PanningFirstValue>0</PanningFirstValue>
  <PanningNextValue>0</PanningNextValue>
  <PanningFirstSize>0</PanningFirstSize>
  <PanningLFOApply>false</PanningLFOApply>
  <PanningLFO1>1</PanningLFO1>
  <PanningLFOPhase1>0</PanningLFOPhase1>
  <PanningLFOFrequency1>3</PanningLFOFrequency1>
  <PanningLFOAmount1>27</PanningLFOAmount1>
  <PanningLFO2>1</PanningLFO2>
  <PanningLFOPhase2>0</PanningLFOPhase2>
  <PanningLFOFrequency2>3</PanningLFOFrequency2>
  <PanningLFOAmount2>27</PanningLFOAmount2>
  <CutoffApply>true</CutoffApply>
  <CutoffScheme>0.28169015049934,0,0.056338027119637,0.084507040679455</CutoffScheme>
  <CutoffPointSequences>0,1,2,10</CutoffPointSequences>
  <CutoffSchemeSize>11</CutoffSchemeSize>
  <CutoffDrawType>3</CutoffDrawType>
  <CutoffEnabled>true</CutoffEnabled>
  <CutoffLoopType>1</CutoffLoopType>
  <CutoffLoopStart>1</CutoffLoopStart>
  <CutoffLoopEnd>10</CutoffLoopEnd>
  <CutoffSustain>2</CutoffSustain>
  <CutoffLFOApply>true</CutoffLFOApply>
  <CutoffLFO>2</CutoffLFO>
  <CutoffLFOPhase>0</CutoffLFOPhase>
  <CutoffLFOFrequency>1</CutoffLFOFrequency>
  <CutoffLFOAmount>16</CutoffLFOAmount>
  <CutoffFollower>false</CutoffFollower>
  <CutoffFollowerAttack>20</CutoffFollowerAttack>
  <CutoffFollowerRelease>80</CutoffFollowerRelease>
  <CutoffFollowerAmount>59</CutoffFollowerAmount>
  <ResonanceApply>true</ResonanceApply>
  <ResonanceScheme>0.8873239159584</ResonanceScheme>
  <ResonancePointSequences>1</ResonancePointSequences>
  <ResonanceSchemeSize>97</ResonanceSchemeSize>
  <ResonanceDrawType>3</ResonanceDrawType>
  <ResonanceEnabled>true</ResonanceEnabled>
  <ResonanceLoopType>1</ResonanceLoopType>
  <ResonanceLoopStart>0</ResonanceLoopStart>
  <ResonanceLoopEnd>71</ResonanceLoopEnd>
  <ResonanceSustain>-1</ResonanceSustain>
  <ResonanceLFOApply>false</ResonanceLFOApply>
  <ResonanceLFO>1</ResonanceLFO>
  <ResonanceLFOPhase>0</ResonanceLFOPhase>
  <ResonanceLFOFrequency>3</ResonanceLFOFrequency>
  <ResonanceLFOAmount>27</ResonanceLFOAmount>
  <ResonanceFollower>false</ResonanceFollower>
  <ResonanceFollowerAttack>20</ResonanceFollowerAttack>
  <ResonanceFollowerRelease>80</ResonanceFollowerRelease>
  <ResonanceFollowerAmount>100</ResonanceFollowerAmount>
  <CutResFilterType>6</CutResFilterType>
</EnvelopePresetTable>
